ip2location_io-1.1.0.dist-info/licenses/LICENSE.TXT
ip2locationio/__init__.py
ip2locationio/common.py
ip2locationio/configuration.py
ip2locationio/domainwhois.py
ip2locationio/hosteddomain.py
ip2locationio/ipgeolocation.py
ip2location_io-1.1.0.dist-info/METADATA
ip2location_io-1.1.0.dist-info/WHEEL
ip2location_io-1.1.0.dist-info/top_level.txt
ip2location_io-1.1.0.dist-info/RECORD
